Metadata-Version: 2.1
Name: phuntsho
Version: 0.0.1
Summary: A python package for phuntsho Bhutan.
Home-page: https://github.com/PhuntshoBhutan/phuntsho
Author: Phuntsho Bhutan
Author-email: p.phuntsho.bhutan@gmail.com
License: MIT license
Keywords: phuntsho
Classifier: Development Status :: 2 - Pre-Alpha
Classifier: Intended Audience :: Developers
Classifier: License :: OSI Approved :: MIT License
Classifier: Natural Language :: English
Classifier: Programming Language :: Python :: 3
Classifier: Programming Language :: Python :: 3.7
Classifier: Programming Language :: Python :: 3.8
Classifier: Programming Language :: Python :: 3.9
Classifier: Programming Language :: Python :: 3.10
Requires-Python: >=3.7
License-File: LICENSE
